financedatascraperonline/HistoricalDailyStockPricesAPI.py
financedatascraperonline/InterestRatesScrapedData.py
financedatascraperonline/__init__.py
financedatascraperonline-0.1.2.dist-info/LICENSE.txt
financedatascraperonline-0.1.2.dist-info/METADATA
financedatascraperonline-0.1.2.dist-info/WHEEL
financedatascraperonline-0.1.2.dist-info/top_level.txt
financedatascraperonline-0.1.2.dist-info/RECORD
