Metadata-Version: 2.2
Name: financedatascraperonline
Version: 0.1.2
Summary: Library for scraping financial data from online sources
Author: Avilasha Jinia Haldar
License-File: LICENSE.txt
Requires-Dist: pandas
Requires-Dist: numpy
Requires-Dist: requests
Requires-Dist: lxml
Requires-Dist: yfinance
Dynamic: author
Dynamic: description
Dynamic: description-content-type
Dynamic: requires-dist
Dynamic: summary
